{
  "experiment_A": [
    {
      "L": 20,
      "mean_n_cols": 25.0,
      "oracle": [
        [
          0.0,
          290.0,
          4.0,
          6.0,
          0.0
        ],
        [
          0.0,
          5801.0,
          114.0,
          75.0,
          279.0
        ],
        [
          0.0,
          101.0,
          3.0,
          1.0,
          16.0
        ],
        [
          0.0,
          77.0,
          0.0,
          1.0,
          5.0
        ],
        [
          0.0,
          0.0,
          0.0,
          0.0,
          0.0
        ]
      ],
      "bp": [
        [
          0.0,
          289.26732123031286,
          4.745648737425793,
          5.987030032261262,
          1.5951612292198767e-33
        ],
        [
          0.0,
          5754.557618906884,
          161.10851958771045,
          118.31927165358327,
          186.92817306166182
        ],
        [
          0.0,
          96.51301267916165,
          21.900697908022966,
          12.214217519950516,
          60.261328549110274
        ],
        [
          0.0,
          80.57563039347941,
          3.1343904230867694,
          14.954054135266146,
          52.81049838922918
        ],
        [
          0.0,
          0.0,
          0.0,
          0.0,
          0.0
        ]
      ],
      "bias_total_abs": 377.7711013865829,
      "bias_signed": [
        [
          0.0,
          -0.7326787696871406,
          0.7456487374257934,
          -0.012969967738738042,
          1.5951612292198767e-33
        ],
        [
          0.0,
          -46.44238109311573,
          47.10851958771045,
          43.31927165358327,
          -92.07182693833818
        ],
        [
          0.0,
          -4.486987320838352,
          18.900697908022966,
          11.214217519950516,
          44.261328549110274
        ],
        [
          0.0,
          3.5756303934794147,
          3.1343904230867694,
          13.954054135266146,
          47.81049838922918
        ],
        [
          0.0,
          0.0,
          0.0,
          0.0,
          0.0
        ]
      ],
      "oracle_total_count": 6773.0
    },
    {
      "L": 60,
      "mean_n_cols": 69.56666666666666,
      "oracle": [
        [
          0.0,
          287.0,
          8.0,
          5.0,
          0.0
        ],
        [
          0.0,
          16683.0,
          293.0,
          278.0,
          272.0
        ],
        [
          0.0,
          277.0,
          4.0,
          3.0,
          22.0
        ],
        [
          0.0,
          279.0,
          1.0,
          4.0,
          6.0
        ],
        [
          0.0,
          0.0,
          0.0,
          0.0,
          0.0
        ]
      ],
      "bp": [
        [
          0.0,
          290.2203400978415,
          4.858182836432716,
          4.921477065725667,
          4.588397310014456e-91
        ],
        [
          0.0,
          16481.628250335143,
          412.55275325517056,
          337.8559799130102,
          127.5410604449944
        ],
        [
          0.0,
          287.3704812129719,
          90.6477051768944,
          43.14762718529078,
          95.41291819243865
        ],
        [
          0.0,
          300.35897230237197,
          8.520090499095511,
          61.5710050007896,
          77.04602136256025
        ],
        [
          0.0,
          0.0,
          0.0,
          0.0,
          0.0
        ]
      ],
      "bias_total_abs": 899.7549235161393,
      "bias_signed": [
        [
          0.0,
          3.220340097841472,
          -3.141817163567284,
          -0.07852293427433299,
          4.588397310014456e-91
        ],
        [
          0.0,
          -201.3717496648569,
          119.55275325517056,
          59.855979913010174,
          -144.4589395550056
        ],
        [
          0.0,
          10.370481212971924,
          86.6477051768944,
          40.14762718529078,
          73.41291819243865
        ],
        [
          0.0,
          21.358972302371967,
          7.520090499095511,
          57.5710050007896,
          71.04602136256025
        ],
        [
          0.0,
          0.0,
          0.0,
          0.0,
          0.0
        ]
      ],
      "oracle_total_count": 18422.0
    },
    {
      "L": 120,
      "mean_n_cols": 139.23333333333332,
      "oracle": [
        [
          0.0,
          288.0,
          4.0,
          8.0,
          0.0
        ],
        [
          0.0,
          34159.0,
          555.0,
          530.0,
          280.0
        ],
        [
          0.0,
          535.0,
          11.0,
          10.0,
          17.0
        ],
        [
          0.0,
          542.0,
          3.0,
          8.0,
          3.0
        ],
        [
          0.0,
          0.0,
          0.0,
          0.0,
          0.0
        ]
      ],
      "bp": [
        [
          0.0,
          287.15810161184277,
          4.808012915573788,
          8.033885472583192,
          7.500926330583438e-189
        ],
        [
          0.0,
          33696.05469302203,
          749.3112085572087,
          589.4086974945287,
          102.84486376407796
        ],
        [
          0.0,
          597.1002502929189,
          261.4078462381988,
          67.8144582500366,
          103.14858608998277
        ],
        [
          0.0,
          557.3064179110647,
          13.944073160146864,
          156.82979244887014,
          94.00655014594328
        ],
        [
          0.0,
          0.0,
          0.0,
          0.0,
          0.0
        ]
      ],
      "bias_total_abs": 1618.0621205791058,
      "bias_signed": [
        [
          0.0,
          -0.8418983881572331,
          0.8080129155737881,
          0.033885472583191856,
          7.500926330583438e-189
        ],
        [
          0.0,
          -462.9453069779702,
          194.31120855720872,
          59.408697494528724,
          -177.15513623592204
        ],
        [
          0.0,
          62.10025029291887,
          250.40784623819877,
          57.814458250036594,
          86.14858608998277
        ],
        [
          0.0,
          15.306417911064727,
          10.944073160146864,
          148.82979244887014,
          91.00655014594328
        ],
        [
          0.0,
          0.0,
          0.0,
          0.0,
          0.0
        ]
      ],
      "oracle_total_count": 36953.0
    },
    {
      "L": 240,
      "mean_n_cols": 273.3,
      "oracle": [
        [
          0.0,
          291.0,
          3.0,
          6.0,
          0.0
        ],
        [
          0.0,
          67789.0,
          1044.0,
          1078.0,
          279.0
        ],
        [
          0.0,
          1022.0,
          14.0,
          18.0,
          17.0
        ],
        [
          0.0,
          1088.0,
          10.0,
          22.0,
          4.0
        ],
        [
          0.0,
          0.0,
          0.0,
          0.0,
          0.0
        ]
      ],
      "bp": [
        [
          0.0,
          291.14629151672375,
          4.7414144666446125,
          4.112294016631735,
          0.0
        ],
        [
          0.0,
          66827.93174195198,
          1375.74131946814,
          1129.907553669831,
          85.22763375729802
        ],
        [
          0.0,
          1205.6585782471648,
          543.7337427084321,
          104.05672196587717,
          101.11109725945491
        ],
        [
          0.0,
          1094.0716371313436,
          30.343663537733434,
          402.74357157378813,
          113.66126898324015
        ],
        [
          0.0,
          0.0,
          0.0,
          0.0,
          0.0
        ]
      ],
      "bias_total_abs": 2942.6451908024646,
      "bias_signed": [
        [
          0.0,
          0.14629151672374974,
          1.7414144666446125,
          -1.8877059833682646,
          0.0
        ],
        [
          0.0,
          -961.0682580480207,
          331.7413194681401,
          51.90755366983103,
          -193.772366242702
        ],
        [
          0.0,
          183.65857824716477,
          529.7337427084321,
          86.05672196587717,
          84.11109725945491
        ],
        [
          0.0,
          6.07163713134355,
          20.343663537733434,
          380.74357157378813,
          109.66126898324015
        ],
        [
          0.0,
          0.0,
          0.0,
          0.0,
          0.0
        ]
      ],
      "oracle_total_count": 72685.0
    }
  ],
  "experiment_B": {
    "truth_ins": 0.04,
    "truth_del": 0.05,
    "history": [
      {
        "iter": 0,
        "ins": 0.04,
        "del": 0.05,
        "ext": 0.0
      },
      {
        "iter": 1,
        "ins": 0.11409358309545933,
        "del": 0.11552591201285922,
        "ext": 4.0444783371536396e-05
      },
      {
        "iter": 2,
        "ins": 0.11636486151432879,
        "del": 0.11782754824284541,
        "ext": 9.264054557343957e-05
      },
      {
        "iter": 3,
        "ins": 0.11643786461959503,
        "del": 0.1179015880526327,
        "ext": 0.00015942232155755553
      },
      {
        "iter": 4,
        "ins": 0.11640774999523736,
        "del": 0.11787120432800875,
        "ext": 0.000245032688397622
      },
      {
        "iter": 5,
        "ins": 0.11636425153142986,
        "del": 0.11782729751818707,
        "ext": 0.00035469354213147497
      },
      {
        "iter": 6,
        "ins": 0.11630805973043809,
        "del": 0.11777057618055649,
        "ext": 0.0004949815577458877
      },
      {
        "iter": 7,
        "ins": 0.11623661677543144,
        "del": 0.11769846095475324,
        "ext": 0.0006741567767771445
      },
      {
        "iter": 8,
        "ins": 0.11614614052893266,
        "del": 0.11760713513770796,
        "ext": 0.0009025229300380208
      },
      {
        "iter": 9,
        "ins": 0.11603206520344791,
        "del": 0.11749199157937079,
        "ext": 0.0011928210119036078
      },
      {
        "iter": 10,
        "ins": 0.11588903011433656,
        "del": 0.11734762180467471,
        "ext": 0.0015606299270601166
      },
      {
        "iter": 11,
        "ins": 0.11571092282983442,
        "del": 0.11716786016041565,
        "ext": 0.0020247274578806965
      },
      {
        "iter": 12,
        "ins": 0.11549104668293897,
        "del": 0.11694595374822501,
        "ext": 0.002607336764845782
      },
      {
        "iter": 13,
        "ins": 0.1152228868970991,
        "del": 0.11667533840516031,
        "ext": 0.003334155223855283
      },
      {
        "iter": 14,
        "ins": 0.11489906072026232,
        "del": 0.11634857458183136,
        "ext": 0.004234009477989485
      },
      {
        "iter": 15,
        "ins": 0.11451458626742468,
        "del": 0.1159606573051319,
        "ext": 0.005338031809451439
      },
      {
        "iter": 16,
        "ins": 0.11406685429405014,
        "del": 0.11550898550208112,
        "ext": 0.006678194824467066
      },
      {
        "iter": 17,
        "ins": 0.11355555114992905,
        "del": 0.11499328088049068,
        "ext": 0.008285166035094021
      },
      {
        "iter": 18,
        "ins": 0.11298609760189708,
        "del": 0.11441906820026228,
        "ext": 0.010185671689783321
      },
      {
        "iter": 19,
        "ins": 0.11236785043610227,
        "del": 0.11379584993325531,
        "ext": 0.012399596355498749
      },
      {
        "iter": 20,
        "ins": 0.11171757540007991,
        "del": 0.11314062175288449,
        "ext": 0.014937410616503576
      },
      {
        "iter": 21,
        "ins": 0.11105339722873382,
        "del": 0.11247174236411832,
        "ext": 0.0177983518613199
      },
      {
        "iter": 22,
        "ins": 0.11039593424660624,
        "del": 0.1118100831104174,
        "ext": 0.02096994502462609
      },
      {
        "iter": 23,
        "ins": 0.10976383315217382,
        "del": 0.1111745039611937,
        "ext": 0.02442880306626631
      },
      {
        "iter": 24,
        "ins": 0.10917688080818776,
        "del": 0.11058501817823997,
        "ext": 0.02814293266698467
      },
      {
        "iter": 25,
        "ins": 0.10864722320558692,
        "del": 0.11005388664732826,
        "ext": 0.032074307585335096
      },
      {
        "iter": 26,
        "ins": 0.1081838975200101,
        "del": 0.10959021957842072,
        "ext": 0.03618188640282853
      },
      {
        "iter": 27,
        "ins": 0.10779038263237956,
        "del": 0.10919749641492955,
        "ext": 0.04042430001349
      },
      {
        "iter": 28,
        "ins": 0.10746538211374565,
        "del": 0.10887436416911808,
        "ext": 0.044762006319493536
      },
      {
        "iter": 29,
        "ins": 0.10720688131400373,
        "del": 0.10861874107128884,
        "ext": 0.04915858319337452
      },
      {
        "iter": 30,
        "ins": 0.10700979620865805,
        "del": 0.1084254399726539,
        "ext": 0.0535815924706837
      }
    ],
    "fit_ins": [
      0.11291687542716618,
      0.040000000027397335,
      20.136102398573215
    ],
    "fit_del": [
      0.11435423405404235,
      0.05,
      22.782299794919624
    ]
  }
}